google/shopping/merchant_productstudio/__init__.py
google/shopping/merchant_productstudio/gapic_version.py
google/shopping/merchant_productstudio/py.typed
google/shopping/merchant_productstudio_v1alpha/__init__.py
google/shopping/merchant_productstudio_v1alpha/gapic_metadata.json
google/shopping/merchant_productstudio_v1alpha/gapic_version.py
google/shopping/merchant_productstudio_v1alpha/py.typed
google/shopping/merchant_productstudio_v1alpha/services/__init__.py
google/shopping/merchant_productstudio_v1alpha/services/image_service/__init__.py
google/shopping/merchant_productstudio_v1alpha/services/image_service/async_client.py
google/shopping/merchant_productstudio_v1alpha/services/image_service/client.py
google/shopping/merchant_productstudio_v1alpha/services/image_service/transports/__init__.py
google/shopping/merchant_productstudio_v1alpha/services/image_service/transports/base.py
google/shopping/merchant_productstudio_v1alpha/services/image_service/transports/grpc.py
google/shopping/merchant_productstudio_v1alpha/services/image_service/transports/grpc_asyncio.py
google/shopping/merchant_productstudio_v1alpha/services/image_service/transports/rest.py
google/shopping/merchant_productstudio_v1alpha/services/image_service/transports/rest_base.py
google/shopping/merchant_productstudio_v1alpha/services/text_suggestions_service/__init__.py
google/shopping/merchant_productstudio_v1alpha/services/text_suggestions_service/async_client.py
google/shopping/merchant_productstudio_v1alpha/services/text_suggestions_service/client.py
google/shopping/merchant_productstudio_v1alpha/services/text_suggestions_service/transports/__init__.py
google/shopping/merchant_productstudio_v1alpha/services/text_suggestions_service/transports/base.py
google/shopping/merchant_productstudio_v1alpha/services/text_suggestions_service/transports/grpc.py
google/shopping/merchant_productstudio_v1alpha/services/text_suggestions_service/transports/grpc_asyncio.py
google_shopping_merchant_productstudio-0.3.0.dist-info/licenses/LICENSE
google_shopping_merchant_productstudio-0.3.0.dist-info/METADATA
google_shopping_merchant_productstudio-0.3.0.dist-info/WHEEL
google_shopping_merchant_productstudio-0.3.0.dist-info/top_level.txt
google_shopping_merchant_productstudio-0.3.0.dist-info/RECORD
